{
 "actions": [],
 "allow_rename": 1,
 "creation": "2025-05-22 15:05:50.293904",
 "doctype": "DocType",
 "engine": "InnoDB",
 "field_order": [
  "bale_barcode",
  "weight",
  "rate",
  "lot_number",
  "item_grade",
  "item_sub_grade"
 ],
 "fields": [
  {
   "fieldname": "bale_barcode",
   "fieldtype": "Data",
   "in_list_view": 1,
   "label": "Bale Barcode",
   "reqd": 1
  },
  {
   "fetch_from": "bale_barcode.batch_qty",
   "fieldname": "weight",
   "fieldtype": "Read Only",
   "in_list_view": 1,
   "label": "Weight"
  },
  {
   "fieldname": "lot_number",
   "fieldtype": "Read Only",
   "label": "Lot Number"
  },
  {
   "fieldname": "item_grade",
   "fieldtype": "Read Only",
   "label": "Item Grade"
  },
  {
   "fieldname": "item_sub_grade",
   "fieldtype": "Read Only",
   "label": "Item Sub Grade"
  },
  {
   "fieldname": "rate",
   "fieldtype": "Read Only",
   "label": "Rate"
  }
 ],
 "grid_page_length": 50,
 "index_web_pages_for_search": 1,
 "istable": 1,
 "links": [],
 "modified": "2025-05-23 16:17:11.186789",
 "modified_by": "Administrator",
 "module": "Leaf Procurement",
 "name": "Goods Transfer Note Items",
 "owner": "Administrator",
 "permissions": [],
 "row_format": "Dynamic",
 "sort_field": "modified",
 "sort_order": "DESC",
 "states": []
}